ploy/__init__.py
ploy/common.py
ploy/config.py
ploy/hookspecs.py
ploy/plain.py
ploy/proxy.py
ploy/template.py
ploy/tests/__init__.py
ploy/tests/dummy_plugin.py
ploy/tests/dummy_proxy_plugin.py
ploy/tests/test_common.py
ploy/tests/test_config.py
ploy/tests/test_plain.py
ploy/tests/test_ploy.py
ploy/tests/test_proxy.py
ploy/tests/test_template.py
ploy_pytest_plugin/__init__.py
ploy-2.0.1.dist-info/LICENSE.txt
ploy-2.0.1.dist-info/METADATA
ploy-2.0.1.dist-info/WHEEL
ploy-2.0.1.dist-info/entry_points.txt
ploy-2.0.1.dist-info/pbr.json
ploy-2.0.1.dist-info/top_level.txt
ploy-2.0.1.dist-info/RECORD
