Metadata-Version: 2.1
Name: ploy
Version: 2.0.1
Summary: A tool to manage servers through a central configuration. Plugins allow provisioning, configuration and other management tasks.
Home-page: http://github.com/ployground/ploy
Author: Florian Schulze
Author-email: florian.schulze@gmx.net
License: BSD 3-Clause License
Platform: UNKNOWN
Classifier: Environment :: Console
Classifier: Intended Audience :: System Administrators
Classifier: Programming Language :: Python :: 2.7
Classifier: Programming Language :: Python :: 3.7
Classifier: Programming Language :: Python :: 3.8
Classifier: Programming Language :: Python :: 3.9
Classifier: Programming Language :: Python :: 3.10
Classifier: Topic :: System :: Installation/Setup
Classifier: Topic :: System :: Systems Administration
Requires-Python: >=2.7, !=3.0.*, !=3.1.*, !=3.2.*, !=3.3.*, !=3.4.*, !=3.5.*, !=3.6.*
License-File: LICENSE.txt
Requires-Dist: attrs
Requires-Dist: lazy
Requires-Dist: paramiko
Requires-Dist: pluggy
Requires-Dist: ruamel.yaml
Requires-Dist: importlib.metadata ; python_version < "3.8"
